flacfile/__init__.py
flacfile/__native__.cp39-win_amd64.pyd
flacfile-0.0.1.dist-info/METADATA
flacfile-0.0.1.dist-info/WHEEL
flacfile-0.0.1.dist-info/top_level.txt
flacfile-0.0.1.dist-info/RECORD
